bamboo_crawler/__init__.py
bamboo_crawler/__main__.py
bamboo_crawler/_version.py
bamboo_crawler/cli.py
bamboo_crawler/job.py
bamboo_crawler/parser.py
bamboo_crawler/task.py
bamboo_crawler-0.2.1.data/scripts/__main__.py
bamboo_crawler-0.2.1.dist-info/LICENSE
bamboo_crawler-0.2.1.dist-info/METADATA
bamboo_crawler-0.2.1.dist-info/WHEEL
bamboo_crawler-0.2.1.dist-info/entry_points.txt
bamboo_crawler-0.2.1.dist-info/top_level.txt
bamboo_crawler-0.2.1.dist-info/RECORD
