Metadata-Version: 2.1
Name: bamboo-crawler
Version: 0.2.1
Summary: a hobby crawler
Home-page: https://github.com/kitsuyui/bamboo-crawler
Author: Yui Kitsu
Author-email: kitsuyui+github@kitsuyui.com
License: BSD-3-Clause
Classifier: Development Status :: 3 - Alpha
Classifier: Topic :: Internet :: WWW/HTTP
Classifier: License :: OSI Approved :: BSD License
Classifier: Programming Language :: Python :: 3.8
Classifier: Programming Language :: Python :: 3.9
Classifier: Programming Language :: Python :: 3.10
Classifier: Programming Language :: Python :: 3.11
Classifier: Intended Audience :: Developers
Requires-Python: >=3.8
License-File: LICENSE
Requires-Dist: boto3
Requires-Dist: cssselect
Requires-Dist: lxml
Requires-Dist: requests
Requires-Dist: PyYAML
Requires-Dist: SQLAlchemy
Requires-Dist: jinja2
Provides-Extra: dev
Requires-Dist: flake8 ; extra == 'dev'
Requires-Dist: nose ; extra == 'dev'
Requires-Dist: pyformat ; extra == 'dev'
Requires-Dist: moto[server] ; extra == 'dev'
Requires-Dist: mypy ; extra == 'dev'
Requires-Dist: httpbin ; extra == 'dev'
